telemc/__init__.py
telemc/controller.py
telemc/recorder.py
telemc/telemc.py
telemc/cli/__init__.py
telemc/cli/telemc.py
telemc-ck/__init__.py
telemc-ck/controller.py
telemc-ck/recorder.py
telemc-ck/telemc.py
telemc-ck/cli/__init__.py
telemc-ck/cli/telemc.py
telemck/__init__.py
telemck/controller.py
telemck/recorder.py
telemck/telemc.py
telemck/cli/__init__.py
telemck/cli/telemc.py
tests/__init__.py
tests/testutil.py
tests/telemc/__init__.py
tests/telemc/test_recorder.py
telemck-0.3.3.dist-info/METADATA
telemck-0.3.3.dist-info/WHEEL
telemck-0.3.3.dist-info/entry_points.txt
telemck-0.3.3.dist-info/top_level.txt
telemck-0.3.3.dist-info/RECORD
