Metadata-Version: 2.1
Name: telemck
Version: 0.3.3
Summary: Python library for accessing telemd monitoring data
Home-page: https://github.com/keniack/telemc-py
Author: Cynthia Marcelino
Author-email: keniack@gmail.com
License: UNKNOWN
Platform: UNKNOWN
Classifier: Programming Language :: Python :: 3
Classifier: Operating System :: OS Independent
Requires-Dist: redis (>=3.2.1)
